ghoshell/__init__.py
ghoshell/container.py
ghoshell/contracts/__init__.py
ghoshell/contracts/cache.py
ghoshell/contracts/logger.py
ghoshell/contracts/meta.py
ghoshell/framework/__init__.py
ghoshell/framework/bootstrapper/__init__.py
ghoshell/framework/bootstrapper/focus.py
ghoshell/framework/bootstrapper/logger.py
ghoshell/framework/contracts/__init__.py
ghoshell/framework/contracts/message_queue.py
ghoshell/framework/contracts/runtime_driver.py
ghoshell/framework/contracts/think_meta_storage.py
ghoshell/framework/ghost/__init__.py
ghoshell/framework/ghost/clone.py
ghoshell/framework/ghost/config.py
ghoshell/framework/ghost/context.py
ghoshell/framework/ghost/focus.py
ghoshell/framework/ghost/ghost.py
ghoshell/framework/ghost/memory.py
ghoshell/framework/ghost/middleware.py
ghoshell/framework/ghost/mind.py
ghoshell/framework/ghost/mindset.py
ghoshell/framework/ghost/operators.py
ghoshell/framework/ghost/providers.py
ghoshell/framework/ghost/runtime.py
ghoshell/framework/ghost/sending.py
ghoshell/framework/ghost/session.py
ghoshell/framework/ghost/stages.py
ghoshell/framework/intentions/__init__.py
ghoshell/framework/intentions/command_intention.py
ghoshell/framework/intentions/llm_tools_intention.py
ghoshell/framework/intentions/text_classifier.py
ghoshell/framework/reactions/__init__.py
ghoshell/framework/reactions/commands.py
ghoshell/framework/reactions/llm_tools.py
ghoshell/framework/shell/__init__.py
ghoshell/framework/shell/messengers.py
ghoshell/framework/shell/shell.py
ghoshell/framework/stages/__init__.py
ghoshell/framework/stages/basic_stage.py
ghoshell/framework/thinks/__init__.py
ghoshell/framework/thinks/single_stage.py
ghoshell/ghost/__init__.py
ghoshell/ghost/context.py
ghoshell/ghost/exceptions.py
ghoshell/ghost/features.py
ghoshell/ghost/ghost.py
ghoshell/ghost/memory.py
ghoshell/ghost/mindset/__init__.py
ghoshell/ghost/mindset/events.py
ghoshell/ghost/mindset/focus.py
ghoshell/ghost/mindset/mind.py
ghoshell/ghost/mindset/mindset.py
ghoshell-0.0.1.dist-info/LICENSE
ghoshell-0.0.1.dist-info/METADATA
ghoshell-0.0.1.dist-info/WHEEL
ghoshell-0.0.1.dist-info/RECORD
