Metadata-Version: 2.1
Name: ghoshell
Version: 0.0.1
Summary: WIP: bot engine
Home-page: https://github.com/thirdgerb/ghost-in-shells
License: MIT
Author: thirdgerb
Author-email: thirdgerb@gmail.com
Requires-Python: >=3.8,<4.0
Classifier: License :: OSI Approved :: MIT License
Classifier: Programming Language :: Python :: 3
Classifier: Programming Language :: Python :: 3.8
Classifier: Programming Language :: Python :: 3.9
Classifier: Programming Language :: Python :: 3.10
Classifier: Programming Language :: Python :: 3.11
Requires-Dist: PyYAML (>=6.0,<7.0)
Requires-Dist: openai (>=0.27.8,<0.28.0)
Requires-Dist: prompt-toolkit (==3)
Requires-Dist: pydantic (==2.0)
Requires-Dist: requests (>=2.31.0,<3.0.0)
Requires-Dist: rich (==13.4)
Project-URL: Repository, https://github.com/thirdgerb/ghost-in-shells.git
